<?xml version="1.0" encoding="utf-8"?>
<!DOCTYPE hibernate-mapping PUBLIC "-//Hibernate/Hibernate Mapping DTD 3.0//EN"
"http://hibernate.sourceforge.net/hibernate-mapping-3.0.dtd">
<!-- 
    Mapping file autogenerated by MyEclipse Persistence Tools
-->
<hibernate-mapping>
    <class name="cn.foritou.model.Average" table="average" catalog="foritou">
        <id name="id" type="java.lang.Integer">
            <column name="id" />
            <generator class="native" />
        </id>
        <property name="tid" type="java.lang.Integer">
            <column name="tid" />
        </property>
        <property name="store" type="java.lang.Double">
            <column name="store" precision="20" scale="4" />
        </property>
        <property name="score" type="java.lang.Double">
            <column name="score" precision="20" scale="4" />
        </property>
        <property name="collection" type="java.lang.Double">
            <column name="collection" precision="20" scale="4" />
        </property>
        <property name="comment" type="java.lang.Double">
            <column name="comment" precision="20" scale="4" />
        </property>
        <property name="sale" type="java.lang.Double">
            <column name="sale" precision="20" scale="4" />
        </property>
        <property name="comsumption" type="java.lang.Double">
            <column name="comsumption" precision="20" scale="4" />
        </property>
    </class>
</hibernate-mapping>
